cr_api/__init__.py
cr_api/client.py
cr_api/client_async.py
cr_api/exceptions.py
cr_api/url.py
cr_api/models/__init__.py
cr_api/models/base.py
cr_api/models/clan.py
cr_api/models/constants.py
cr_api/models/core.py
cr_api/models/player.py
cr-api-0.15.dist-info/LICENSE.txt
cr-api-0.15.dist-info/WHEEL
cr-api-0.15.dist-info/METADATA
cr-api-0.15.dist-info/RECORD
